{"2017.05.26": {"count": 4, "nodes": [{"__typename": "GraphImage", "code": "BSOpdX8BQyN", "comments": {"count": 70}, "comments_disabled": false, "date": 1490805179, "dimensions": {"height": 937, "width": 750}, "display_src": "https://scontent.cdninstagram.com/t51.2885-15/sh0.08/e35/p750x750/18581332_1866033846984514_3376487539023020032_n.jpg", "id": "1481303665926278285", "is_video": false, "likes": {"count": 351}, "owner": {"id": "3252291269"}, "thumbnail_src": "https://scontent.cdninstagram.com/t51.2885-15/s640x640/sh0.08/e35/c0.100.799.799/18581332_1866033846984514_3376487539023020032_n.jpg"}, {"__typename": "GraphImage", "code": "BSEFq62Aczj", "comments": {"count": 35}, "comments_disabled": false, "date": 1490450871, "dimensions": {"height": 922, "width": 750}, "display_src": "https://scontent.cdninstagram.com/t51.2885-15/sh0.08/e35/p750x750/18580166_151521932054474_6085041628395864064_n.jpg", "id": "1478331517318057187", "is_video": false, "likes": {"count": 355}, "owner": {"id": "3252291269"}, "thumbnail_src": "https://scontent.cdninstagram.com/t51.2885-15/s640x640/sh0.08/e35/c0.111.967.967/18580166_151521932054474_6085041628395864064_n.jpg"}, {"__typename": "GraphImage", "code": "BSDiecGgabD", "comments": {"count": 10}, "comments_disabled": false, "date": 1490432419, "dimensions": {"height": 809, "width": 1080}, "display_src": "https://scontent.cdninstagram.com/t51.2885-15/e35/18580504_1365648706817061_8163411319798628352_n.jpg", "id": "1478176728047265475", "is_video": false, "likes": {"count": 271}, "owner": {"id": "3252291269"}, "thumbnail_src": "https://scontent.cdninstagram.com/t51.2885-15/s640x640/sh0.08/e35/c135.0.809.809/18580504_1365648706817061_8163411319798628352_n.jpg"}, {"__typename": "GraphVideo", "code": "BSA2UhbhzV-", "comments": {"count": 39}, "comments_disabled": false, "date": 1490342160, "dimensions": {"height": 640, "width": 640}, "display_src": "https://scontent.cdninstagram.com/t51.2885-15/e15/18580994_1277269039057357_6134907680466141184_n.jpg", "id": "1477419582573983102", "is_video": true, "likes": {"count": 477}, "owner": {"id": "3252291269"}, "thumbnail_src": "https://scontent.cdninstagram.com/t51.2885-15/e15/18580994_1277269039057357_6134907680466141184_n.jpg", "video_views": 3712}], "page_info": {"end_cursor": "AQDBOOzVLDpT8t0MDLqXpfyrO2IDbsbyWZ_SXkjdhNHHGrobPkujpQtwUSF0lnHeccs", "has_next_page": false}}, "2017.05.28": {"count": 4, "nodes": [{"__typename": "GraphImage", "code": "BSOpdX8BQyN", "comments": {"count": 75}, "comments_disabled": false, "date": 1490805179, "dimensions": {"height": 937, "width": 750}, "display_src": "https://scontent.cdninstagram.com/t51.2885-15/sh0.08/e35/p750x750/18581332_1866033846984514_3376487539023020032_n.jpg", "id": "1481303665926278285", "is_video": false, "likes": {"count": 366}, "owner": {"id": "3252291269"}, "thumbnail_src": "https://scontent.cdninstagram.com/t51.2885-15/s640x640/sh0.08/e35/c0.100.799.799/18581332_1866033846984514_3376487539023020032_n.jpg"}, {"__typename": "GraphImage", "code": "BSEFq62Aczj", "comments": {"count": 26}, "comments_disabled": false, "date": 1490450871, "dimensions": {"height": 922, "width": 750}, "display_src": "https://scontent.cdninstagram.com/t51.2885-15/sh0.08/e35/p750x750/18580166_151521932054474_6085041628395864064_n.jpg", "id": "1478331517318057187", "is_video": false, "likes": {"count": 364}, "owner": {"id": "3252291269"}, "thumbnail_src": "https://scontent.cdninstagram.com/t51.2885-15/s640x640/sh0.08/e35/c0.111.967.967/18580166_151521932054474_6085041628395864064_n.jpg"}, {"__typename": "GraphImage", "code": "BSDiecGgabD", "comments": {"count": 10}, "comments_disabled": false, "date": 1490432419, "dimensions": {"height": 809, "width": 1080}, "display_src": "https://scontent.cdninstagram.com/t51.2885-15/e35/18580504_1365648706817061_8163411319798628352_n.jpg", "id": "1478176728047265475", "is_video": false, "likes": {"count": 282}, "owner": {"id": "3252291269"}, "thumbnail_src": "https://scontent.cdninstagram.com/t51.2885-15/s640x640/sh0.08/e35/c135.0.809.809/18580504_1365648706817061_8163411319798628352_n.jpg"}, {"__typename": "GraphVideo", "code": "BSA2UhbhzV-", "comments": {"count": 40}, "comments_disabled": false, "date": 1490342160, "dimensions": {"height": 640, "width": 640}, "display_src": "https://scontent.cdninstagram.com/t51.2885-15/e15/18580994_1277269039057357_6134907680466141184_n.jpg", "id": "1477419582573983102", "is_video": true, "likes": {"count": 497}, "owner": {"id": "3252291269"}, "thumbnail_src": "https://scontent.cdninstagram.com/t51.2885-15/e15/18580994_1277269039057357_6134907680466141184_n.jpg", "video_views": 3851}], "page_info": {"end_cursor": "AQCIC5HxYJtH22UxMn2nYXeu4kLF5mmYKtzsxsP1rNCFYr9ynfW0Ne8INSNtOLznM-g", "has_next_page": false}}, "2017.05.30": {"count": 4, "nodes": [{"__typename": "GraphImage", "code": "BSOpdX8BQyN", "comments": {"count": 75}, "comments_disabled": false, "date": 1490805179, "dimensions": {"height": 937, "width": 750}, "display_src": "https://scontent.cdninstagram.com/t51.2885-15/sh0.08/e35/p750x750/18581332_1866033846984514_3376487539023020032_n.jpg", "id": "1481303665926278285", "is_video": false, "likes": {"count": 380}, "owner": {"id": "3252291269"}, "thumbnail_src": "https://scontent.cdninstagram.com/t51.2885-15/s640x640/sh0.08/e35/c0.100.799.799/18581332_1866033846984514_3376487539023020032_n.jpg"}, {"__typename": "GraphImage", "code": "BSEFq62Aczj", "comments": {"count": 26}, "comments_disabled": false, "date": 1490450871, "dimensions": {"height": 922, "width": 750}, "display_src": "https://scontent.cdninstagram.com/t51.2885-15/sh0.08/e35/p750x750/18580166_151521932054474_6085041628395864064_n.jpg", "id": "1478331517318057187", "is_video": false, "likes": {"count": 378}, "owner": {"id": "3252291269"}, "thumbnail_src": "https://scontent.cdninstagram.com/t51.2885-15/s640x640/sh0.08/e35/c0.111.967.967/18580166_151521932054474_6085041628395864064_n.jpg"}, {"__typename": "GraphImage", "code": "BSDiecGgabD", "comments": {"count": 10}, "comments_disabled": false, "date": 1490432419, "dimensions": {"height": 809, "width": 1080}, "display_src": "https://scontent.cdninstagram.com/t51.2885-15/e35/18580504_1365648706817061_8163411319798628352_n.jpg", "id": "1478176728047265475", "is_video": false, "likes": {"count": 292}, "owner": {"id": "3252291269"}, "thumbnail_src": "https://scontent.cdninstagram.com/t51.2885-15/s640x640/sh0.08/e35/c135.0.809.809/18580504_1365648706817061_8163411319798628352_n.jpg"}, {"__typename": "GraphVideo", "code": "BSA2UhbhzV-", "comments": {"count": 40}, "comments_disabled": false, "date": 1490342160, "dimensions": {"height": 640, "width": 640}, "display_src": "https://scontent.cdninstagram.com/t51.2885-15/e15/18580994_1277269039057357_6134907680466141184_n.jpg", "id": "1477419582573983102", "is_video": true, "likes": {"count": 509}, "owner": {"id": "3252291269"}, "thumbnail_src": "https://scontent.cdninstagram.com/t51.2885-15/e15/18580994_1277269039057357_6134907680466141184_n.jpg", "video_views": 3942}], "page_info": {"end_cursor": "AQDSAHJ4CEN9LavZQe8xZGqnzW68RmqI4FiZMVY4-TutW_t3zlvTbNQd5bIgqTtB-UQ", "has_next_page": false}}, "2017.06.04": {"count": 4, "nodes": [{"__typename": "GraphImage", "code": "BSOpdX8BQyN", "comments": {"count": 79}, "comments_disabled": false, "date": 1490805179, "dimensions": {"height": 1350, "width": 1080}, "display_src": "https://scontent.cdninstagram.com/t51.2885-15/e35/18581332_1866033846984514_3376487539023020032_n.jpg", "gating_info": null, "id": "1481303665926278285", "is_video": false, "likes": {"count": 442}, "media_preview": "ACEqzFjxyeakK7uOM+3vRHk9PQ9PpSM2wEHqcHH40hmjHapCodzyV5BxjPXge1Zssodty8HpjH61PJdGZslSBjGOP09M1SPQ546cUCDc1FNz7migZrCwULu3EY5I4xx9KqhEfk4Bx6nPp6itCdv3Rwe3P4VmrPgbCOQeCOvPY+3f1piQ14s42kfn/wDXNRtG6jmpzOEO7BOPXOPx6U533qCe4oGZ+DRU3FFIDRRvMVkYE5HH4VnrFvyc4571oTMQQAT2qH/lg3/XQfyNMRU8ls4GTn0pS3GPSrCkjBHB9aqydaQxmaKbRQB//9k=", "owner": {"id": "3252291269"}, "thumbnail_src": "https://scontent.cdninstagram.com/t51.2885-15/s640x640/sh0.08/e35/c0.100.799.799/18581332_1866033846984514_3376487539023020032_n.jpg"}, {"__typename": "GraphImage", "code": "BSEFq62Aczj", "comments": {"count": 26}, "comments_disabled": false, "date": 1490450871, "dimensions": {"height": 1327, "width": 1080}, "display_src": "https://scontent.cdninstagram.com/t51.2885-15/e35/18580166_151521932054474_6085041628395864064_n.jpg", "gating_info": null, "id": "1478331517318057187", "is_video": false, "likes": {"count": 429}, "media_preview": "ACIqqIh5I7fyPBrWt8FQD1wKy5VwwAGc9j/+sVbszsc5HPTH4D61lJXRuvdLzRjOMc1EYT0xSSSlZQy8YGPXgnn+mKsNID0496ycUWpsr/Zj6UVL5hopW8yudmZcRrFKoXOMA8896EnVHYnrnj8sVDfFmmwPQCrFhGGyrcn+XSuhrTUyuJJcKwLDgjA/U5/+tUbXLuMcDHPvxVi7RQpRRk8Nx9cVlMje/Hr1FJRRLbLXmyHnf+goqnk+1FVyrsieYmVyWDE5PqauWTfOzH/JzWUK0bf/AFY/H+dEtEVDVl1zmTcOuBz7Z6Y/XNE8aT8nhh3HX6H1qqGIPBI4NNQnFRc15VsN8iUcYBx70VLuPrRVXJ5F5n//2Q==", "owner": {"id": "3252291269"}, "thumbnail_src": "https://scontent.cdninstagram.com/t51.2885-15/s640x640/sh0.08/e35/c0.111.967.967/18580166_151521932054474_6085041628395864064_n.jpg"}, {"__typename": "GraphImage", "code": "BSDiecGgabD", "comments": {"count": 10}, "comments_disabled": false, "date": 1490432419, "dimensions": {"height": 809, "width": 1080}, "display_src": "https://scontent.cdninstagram.com/t51.2885-15/e35/18580504_1365648706817061_8163411319798628352_n.jpg", "gating_info": null, "id": "1478176728047265475", "is_video": false, "likes": {"count": 327}, "media_preview": "ACofYkTDJJ4b8QfcY5FQizccYVsDIbPB/EfqDii01BYgUnBYAALjHAx0PTP50st4izeYg3oYwu3oM5z09vx5qPeV0vyNG07XJ0RZhnbh+4BI49cn+n50wRxRnDZduwwf8n+VJHfxyffHlheh+8fpwO3vStdwY+8zZ6kqf8/yqGne2tjRSXkMdmB4+Uew5/Piq+W9T+dS/bIl4Csfr1/PJprMhJxyM+9Ul5EuXmVQPlYjjAqQhQVK9GHBPTPdTnjP8wRSoyqjcZ3cfQdu341DE2BtblT29+mfy/pWhkKwIOSM/Q4/z+VAeM8ZdT7/ADD/ABpC235Ccj+Fu+PQ0OmKYE6xA/ccH8gf1o8h/f8ASqZTHPb1H+FLg+v86Yj/2Q==", "owner": {"id": "3252291269"}, "thumbnail_src": "https://scontent.cdninstagram.com/t51.2885-15/s640x640/sh0.08/e35/c135.0.809.809/18580504_1365648706817061_8163411319798628352_n.jpg"}, {"__typename": "GraphVideo", "code": "BSA2UhbhzV-", "comments": {"count": 40}, "comments_disabled": false, "date": 1490342160, "dimensions": {"height": 640, "width": 640}, "display_src": "https://scontent.cdninstagram.com/t51.2885-15/e15/18580994_1277269039057357_6134907680466141184_n.jpg", "gating_info": null, "id": "1477419582573983102", "is_video": true, "likes": {"count": 559}, "media_preview": "ACoq6HA/yTTqbRnFAhs8vlIW79vrXPxsZWMjk45AHr71qXE2/gYwM45/DP8AgPSstAW5PNQ9TSLsmWxKBxUvmr7VnlT71ILKQjII59//AK1TZlXRu1majKQVToPvEkZXjseD7849K0qrXNqtxjccbc9gevbkGtTExyQ68CM59Ffn8fL4/I1FA3lybcAbuMAY/HkKx+uMe9ajaeWOfMbj2Az064+g/LHSmR6cIW3bi3t74xk88n8KBiGnCQjihhimYpAa9JS0lMQU00tJQBVlWq1XXqqaBn//2Q==", "owner": {"id": "3252291269"}, "thumbnail_src": "https://scontent.cdninstagram.com/t51.2885-15/e15/18580994_1277269039057357_6134907680466141184_n.jpg", "video_views": 4246}], "page_info": {"end_cursor": "AQCeejGnENAWNQTCVoEn8boj47ONeCeN2-Rhs2qfFsQMND7P002FO994ZI1nIhRG7TE", "has_next_page": false}}}