{"2011-04-21": {"_target": 0.75, "active_passive": 1.0, "coordinates": [-100, -100, -100, -100, -100, -100, -100, -100, -100, -100, -100, -100], "day_night": 0.3333333333333333, "favourites_count": 0, "hashtags_count": 0, "media_count": 0, "mentions": [1, 1, 5, 6, 7, 5, 5, 5, 8, 5], "mentions_count": 10, "source": [1, 1, 1, 1, 1, 1, 1, 1, 1, 1, 1, 1], "source_twitter_or_not": 0, "top_mentions": [1], "week": 1}, "2011-04-22": {"_target": 0.0, "active_passive": 0.8, "coordinates": [-100, -100, -100, -100, -100], "day_night": 0.8, "favourites_count": 0, "hashtags_count": 0, "media_count": 0, "mentions": [1, 23, 21, 24, 21, 1], "mentions_count": 6, "source": [1, 1, 1, 1, 1], "source_twitter_or_not": 0, "top_mentions": [2], "week": 1}, "2011-04-24": {"_target": 0.6666666666666666, "active_passive": 1.0, "coordinates": [-100, -100, -100], "day_night": 1.0, "favourites_count": 0, "hashtags_count": 0, "media_count": 0, "mentions": [2, 1], "mentions_count": 2, "source": [1, 1, 1], "source_twitter_or_not": 0, "top_mentions": [2], "week": 2}, "2011-04-25": {"_target": 0.5, "active_passive": 1.0, "coordinates": [-100, -100, -100, -100, -100, -100, -100, -100, -100, -100, -100], "day_night": 0.7272727272727273, "favourites_count": 0, "hashtags_count": 0, "media_count": 0, "mentions": [1, 2, 3, 4, 1, 4, 3], "mentions_count": 7, "source": [1, 1, 1, 1, 1, 1, 1, 1, 1, 1, 1], "source_twitter_or_not": 0, "top_mentions": [], "week": 2}, "2011-05-09": {"_target": 0.0, "active_passive": 1.0, "coordinates": [-100, -100, -100, -100], "day_night": 0.5, "favourites_count": 0, "hashtags_count": 0, "media_count": 0, "mentions": [9, 10], "mentions_count": 2, "source": [1, 1, 1, 1], "source_twitter_or_not": 0, "top_mentions": [], "week": 2}, "2011-05-10": {"_target": 0.5, "active_passive": 1.0, "coordinates": [-100, -100, -100, -100, -100, -100, -100, -100, -100], "day_night": 1.0, "favourites_count": 0, "hashtags_count": 0, "media_count": 0, "mentions": [3, 3], "mentions_count": 2, "source": [1, 1, 1, 1, 1, 1, 1, 1, 1], "source_twitter_or_not": 0, "top_mentions": [], "week": 1}, "2011-05-19": {"_target": 0.5, "active_passive": 1.0, "coordinates": [-100, -100, -100, -100, -100, -100, -100, -100, -100, -100, -100, -100, -100, -100, -100, -100, -100, -100, -100, -100], "day_night": 1.0, "favourites_count": 0, "hashtags_count": 0, "media_count": 0, "mentions": [25, 26, 27, 27, 16, 21], "mentions_count": 6, "source": [1, 1, 1, 1, 1, 1, 1, 1, 1, 1, 1, 1, 1, 1, 1, 1, 1, 1, 1, 1], "source_twitter_or_not": 0, "top_mentions": [], "week": 1}, "2011-07-31": {"_target": 0.5, "active_passive": 1.0, "coordinates": [-100, -100, -100], "day_night": 1.0, "favourites_count": 0, "hashtags_count": 0, "media_count": 0, "mentions": [20, 21, 22], "mentions_count": 3, "source": [1, 1, 1], "source_twitter_or_not": 0, "top_mentions": [], "week": 2}, "2011-09-21": {"_target": 0.0, "active_passive": 1.0, "coordinates": [-100], "day_night": 1.0, "favourites_count": 0, "hashtags_count": 0, "media_count": 0, "mentions": [19], "mentions_count": 1, "source": [1], "source_twitter_or_not": 0, "top_mentions": [], "week": 1}, "2011-10-06": {"_target": 0.5, "active_passive": 1.0, "coordinates": [-100, -100, -100, -100, -100, -100], "day_night": 0.0, "favourites_count": 0, "hashtags_count": 1, "media_count": 0, "mentions": [14, 15, 15, 16], "mentions_count": 4, "source": [1, 1, 2, 2, 2, 2], "source_twitter_or_not": 0, "top_mentions": [], "week": 1}, "2012-02-08": {"_target": 0.7142857142857143, "active_passive": 1.0, "coordinates": [-100, -100], "day_night": 1.0, "favourites_count": 0, "hashtags_count": 0, "media_count": 0, "mentions": [3], "mentions_count": 1, "source": [1, 1], "source_twitter_or_not": 0, "top_mentions": [3], "week": 1}, "2012-06-26": {"_target": 0.6666666666666666, "active_passive": 1.0, "coordinates": [-100, -100, -100, -100], "day_night": 1.0, "favourites_count": 0, "hashtags_count": 0, "media_count": 0, "mentions": [], "mentions_count": 0, "source": [1, 1, 1, 1], "source_twitter_or_not": 0, "top_mentions": [], "week": 1}, "2013-06-29": {"_target": 0.6666666666666666, "active_passive": 1.0, "coordinates": [-100], "day_night": 1.0, "favourites_count": 0, "hashtags_count": 0, "media_count": 0, "mentions": [], "mentions_count": 0, "source": [1], "source_twitter_or_not": 0, "top_mentions": [], "week": 1}, "2016-01-23": {"_target": 0.5, "active_passive": 1.0, "coordinates": [-100, -100, -100], "day_night": 1.0, "favourites_count": 0, "hashtags_count": 0, "media_count": 1, "mentions": [], "mentions_count": 0, "source": [1, 1, 1], "source_twitter_or_not": 3, "top_mentions": [], "week": 1}, "2016-01-29": {"_target": 0.0, "active_passive": 1.0, "coordinates": [-100], "day_night": 0.0, "favourites_count": 0, "hashtags_count": 0, "media_count": 0, "mentions": [18], "mentions_count": 1, "source": [1], "source_twitter_or_not": 1, "top_mentions": [], "week": 1}, "2016-01-31": {"_target": 0.5, "active_passive": 1.0, "coordinates": [-100, -100, -100], "day_night": 0.3333333333333333, "favourites_count": 0, "hashtags_count": 0, "media_count": 0, "mentions": [28, 29, 29], "mentions_count": 3, "source": [1, 1, 1], "source_twitter_or_not": 3, "top_mentions": [], "week": 2}, "2016-02-13": {"_target": 0.0, "active_passive": 1.0, "coordinates": [-100, -100, -100, -100, -100, -100, -100], "day_night": 0.7142857142857143, "favourites_count": 1, "hashtags_count": 0, "media_count": 0, "mentions": [], "mentions_count": 0, "source": [1, 1, 1, 1, 1, 1, 1], "source_twitter_or_not": 7, "top_mentions": [], "week": 1}, "2016-02-14": {"_target": 0.8333333333333334, "active_passive": 1.0, "coordinates": [-100, -100, -100, -100, -100, -100], "day_night": 0.8333333333333334, "favourites_count": 0, "hashtags_count": 0, "media_count": 0, "mentions": [], "mentions_count": 0, "source": [1, 2, 2, 2, 1, 1], "source_twitter_or_not": 6, "top_mentions": [], "week": 2}, "2016-03-13": {"_target": 0.5, "active_passive": 1.0, "coordinates": [-100, -100, -100], "day_night": 0.3333333333333333, "favourites_count": 0, "hashtags_count": 0, "media_count": 0, "mentions": [3, 15], "mentions_count": 2, "source": [1, 2, 2], "source_twitter_or_not": 3, "top_mentions": [4], "week": 2}, "2016-03-25": {"_target": 0.0, "active_passive": 0.0, "coordinates": [-100], "day_night": 1.0, "favourites_count": 0, "hashtags_count": 0, "media_count": 0, "mentions": [17], "mentions_count": 1, "source": [1], "source_twitter_or_not": 1, "top_mentions": [], "week": 1}, "2016-10-07": {"_target": 0.0, "active_passive": 1.0, "coordinates": [-100, -100], "day_night": 0.0, "favourites_count": 1, "hashtags_count": 0, "media_count": 1, "mentions": [], "mentions_count": 0, "source": [1, 1], "source_twitter_or_not": 2, "top_mentions": [], "week": 1}, "2017-05-07": {"_target": 0.0, "active_passive": 1.0, "coordinates": [-100], "day_night": 1.0, "favourites_count": 1, "hashtags_count": 0, "media_count": 0, "mentions": [], "mentions_count": 0, "source": [1], "source_twitter_or_not": 1, "top_mentions": [], "week": 2}, "2017-05-27": {"_target": 0.8, "active_passive": 0.6, "coordinates": [-100, -100, -100, -100, -100], "day_night": 0.4, "favourites_count": 0, "hashtags_count": 1, "media_count": 1, "mentions": [11, 12, 13], "mentions_count": 3, "source": [1, 1, 1, 1, 1], "source_twitter_or_not": 5, "top_mentions": [], "week": 1}}